MANIFEST.in
README.md
setup.py
django_twitter_bootstrap_form.egg-info/PKG-INFO
django_twitter_bootstrap_form.egg-info/SOURCES.txt
django_twitter_bootstrap_form.egg-info/dependency_links.txt
django_twitter_bootstrap_form.egg-info/requires.txt
django_twitter_bootstrap_form.egg-info/top_level.txt
twitter_bootstrap_form/__init__.py
twitter_bootstrap_form/models.py
twitter_bootstrap_form/templates/twitter_bootstrap_form/fields.html
twitter_bootstrap_form/templates/twitter_bootstrap_form/form.html
twitter_bootstrap_form/templatetags/__init__.py
twitter_bootstrap_form/templatetags/twitter_bootstrap_form.py