Metadata-Version: 1.0
Name: django-twitter-bootstrap-form
Version: 0.1.0
Summary: Twitter Bootstrap Form
Home-page: https://github.com/PragmaticMates/django-twitter-bootstrap-form
Author: Pragmatic Mates
Author-email: info@pragmaticmates.com
License: BSD License
Platform: UNKNOWN
Classifier: Programming Language :: Python
Classifier: Programming Language :: Python :: 2.5
Classifier: Programming Language :: Python :: 2.6
Classifier: Programming Language :: Python :: 2.7
Classifier: Operating System :: OS Independent
Classifier: Environment :: Web Environment
Classifier: Intended Audience :: Developers
Classifier: Framework :: Django
Classifier: License :: OSI Approved :: BSD License
